attachvolume/__init__.py
attachvolume-0.1.0.dist-info/METADATA
attachvolume-0.1.0.dist-info/WHEEL
attachvolume-0.1.0.dist-info/entry_points.txt
attachvolume-0.1.0.dist-info/top_level.txt
attachvolume-0.1.0.dist-info/RECORD
